WuaiPojieLuntanjinghuaJi2019DierBufen/README.md
WuaiPojieLuntanjinghuaJi2019DierBufen/__init__.py
WuaiPojieLuntanjinghuaJi2019DierBufen/__main__.py
WuaiPojieLuntanjinghuaJi2019DierBufen/file.epub
WuaiPojieLuntanjinghuaJi2019DierBufen/index.html
WuaiPojieLuntanjinghuaJi2019DierBufen/css/__init__.py
WuaiPojieLuntanjinghuaJi2019DierBufen/css/annotations.css
WuaiPojieLuntanjinghuaJi2019DierBufen/css/main.css
WuaiPojieLuntanjinghuaJi2019DierBufen/css/normalize.css
WuaiPojieLuntanjinghuaJi2019DierBufen/css/popup.css
WuaiPojieLuntanjinghuaJi2019DierBufen/font/__init__.py
WuaiPojieLuntanjinghuaJi2019DierBufen/font/fontello.eot
WuaiPojieLuntanjinghuaJi2019DierBufen/font/fontello.svg
WuaiPojieLuntanjinghuaJi2019DierBufen/font/fontello.ttf
WuaiPojieLuntanjinghuaJi2019DierBufen/font/fontello.woff
WuaiPojieLuntanjinghuaJi2019DierBufen/img/__init__.py
WuaiPojieLuntanjinghuaJi2019DierBufen/img/annotator-glyph-sprite.png
WuaiPojieLuntanjinghuaJi2019DierBufen/img/annotator-icon-sprite.png
WuaiPojieLuntanjinghuaJi2019DierBufen/img/apple-touch-icon.png
WuaiPojieLuntanjinghuaJi2019DierBufen/img/cancelfullscreen.png
WuaiPojieLuntanjinghuaJi2019DierBufen/img/close.png
WuaiPojieLuntanjinghuaJi2019DierBufen/img/fullscreen.png
WuaiPojieLuntanjinghuaJi2019DierBufen/img/loader.gif
WuaiPojieLuntanjinghuaJi2019DierBufen/img/menu-icon.png
WuaiPojieLuntanjinghuaJi2019DierBufen/img/save.png
WuaiPojieLuntanjinghuaJi2019DierBufen/img/saved.png
WuaiPojieLuntanjinghuaJi2019DierBufen/img/settings-s.png
WuaiPojieLuntanjinghuaJi2019DierBufen/img/settings.png
WuaiPojieLuntanjinghuaJi2019DierBufen/img/star.png
WuaiPojieLuntanjinghuaJi2019DierBufen/js/__init__.py
WuaiPojieLuntanjinghuaJi2019DierBufen/js/epub.js
WuaiPojieLuntanjinghuaJi2019DierBufen/js/epub.min.js
WuaiPojieLuntanjinghuaJi2019DierBufen/js/epub.min.map
WuaiPojieLuntanjinghuaJi2019DierBufen/js/hooks.min.js
WuaiPojieLuntanjinghuaJi2019DierBufen/js/hooks.min.map
WuaiPojieLuntanjinghuaJi2019DierBufen/js/reader.js
wuai_pojie_luntanjinghua_ji_2019_dier_bufen-2024.3.5.0.dist-info/METADATA
wuai_pojie_luntanjinghua_ji_2019_dier_bufen-2024.3.5.0.dist-info/WHEEL
wuai_pojie_luntanjinghua_ji_2019_dier_bufen-2024.3.5.0.dist-info/entry_points.txt
wuai_pojie_luntanjinghua_ji_2019_dier_bufen-2024.3.5.0.dist-info/top_level.txt
wuai_pojie_luntanjinghua_ji_2019_dier_bufen-2024.3.5.0.dist-info/RECORD
